deinterf/__init__.py
deinterf/_version.py
deinterf/py.typed
deinterf/compensator/__init__.py
deinterf/compensator/tmi/__init__.py
deinterf/compensator/tmi/linear/__init__.py
deinterf/compensator/tmi/linear/_term.py
deinterf/compensator/tmi/linear/terms.py
deinterf/compensator/tmi/linear/tolles_lawson.py
deinterf/foundation/__init__.py
deinterf/foundation/_term.py
deinterf/foundation/sensors.py
deinterf/metrics/__init__.py
deinterf/metrics/fom.py
deinterf/utils/__init__.py
deinterf/utils/filter.py
deinterf/utils/transform.py
deinterf/utils/data_ioc/__init__.py
deinterf/utils/data_ioc/_data.py
deinterf/utils/data_ioc/_data_ndarray.py
deinterf-1.2.0.dist-info/METADATA
deinterf-1.2.0.dist-info/WHEEL
deinterf-1.2.0.dist-info/licenses/LICENSE
deinterf-1.2.0.dist-info/RECORD
