Metadata-Version: 2.4
Name: deinterf
Version: 1.2.0
Summary: Aeromagnetic interference compensation based on the Tolles–Lawson (T-L) model. Modular IoC pipeline with a scikit-style API.
Project-URL: Homepage, https://github.com/dyuu7/deinterf
Project-URL: Repository, https://github.com/dyuu7/deinterf
Project-URL: Issues, https://github.com/dyuu7/deinterf/issues
Author: dyuu7
License: MIT
License-File: LICENSE
Classifier: License :: OSI Approved :: MIT License
Classifier: Operating System :: OS Independent
Classifier: Programming Language :: Python :: 3.9
Classifier: Programming Language :: Python :: 3.10
Classifier: Programming Language :: Python :: 3.11
Classifier: Programming Language :: Python :: 3.12
Classifier: Typing :: Typed
Requires-Python: >=3.9
Requires-Dist: numpy>=1.26.4
Requires-Dist: ppigrf>=1.0.2
Requires-Dist: scikit-learn>=1.4.0
Requires-Dist: scipy>=1.12.0
Requires-Dist: sgl2020>=0.1.1
Requires-Dist: typing-extensions>=4.10.0; python_version < '3.11'
Provides-Extra: plot
Requires-Dist: matplotlib>=3.8.3; extra == 'plot'
